beeth0ven_internal_python_graphql_client/__init__.py
beeth0ven_internal_python_graphql_client-0.0.2.dist-info/LICENSE
beeth0ven_internal_python_graphql_client-0.0.2.dist-info/METADATA
beeth0ven_internal_python_graphql_client-0.0.2.dist-info/WHEEL
beeth0ven_internal_python_graphql_client-0.0.2.dist-info/top_level.txt
beeth0ven_internal_python_graphql_client-0.0.2.dist-info/RECORD
